selget/__init__.py
selget/_version.py
selget/selget.py
selget-1.0.3.dist-info/entry_points.txt
selget-1.0.3.dist-info/licenses/LICENSE
selget-1.0.3.dist-info/WHEEL
selget-1.0.3.dist-info/METADATA
selget-1.0.3.dist-info/RECORD
