Metadata-Version: 2.4
Name: selget
Version: 1.0.3
Summary: Selenium GET
Author: Darron Broad
Requires-Python: >=3.9
Classifier: Programming Language :: Python :: 3
Classifier: Operating System :: OS Independent
License-File: LICENSE
Requires-Dist: lxml
Requires-Dist: beautifulsoup4
Requires-Dist: selenium
Project-URL: Documentation, https://wiki.kewl.org/projects:selget
